crawlerbox/__init__.py
crawlerbox/__main__.py
crawlerbox/_version.py
crawlerbox/additional_info.py
crawlerbox/cisco_investigate.py
crawlerbox/config.py
crawlerbox/crawl_page.py
crawlerbox/network_manager.py
crawlerbox/personalized_config.py
crawlerbox/phish_logger.py
crawlerbox/phishdb_layer.py
crawlerbox/phishdb_schema.py
crawlerbox/phishparser.py
crawlerbox/shodan_enrichment.py
crawlerbox-0.0.3.dist-info/licenses/LICENSE
crawlerbox-0.0.3.dist-info/METADATA
crawlerbox-0.0.3.dist-info/WHEEL
crawlerbox-0.0.3.dist-info/entry_points.txt
crawlerbox-0.0.3.dist-info/top_level.txt
crawlerbox-0.0.3.dist-info/RECORD
