Metadata-Version: 2.4
Name: CrawlerBox
Version: 0.0.3
Summary: An analysis pipeline for parsing and crawling evasive phishing emails
Home-page: https://github.com/AmadeusITGroup/CrawlerBox
Author: Elyssa Boulila
Author-email: elyssa.boulila@amadeus.com
Classifier: Development Status :: 5 - Production/Stable
Classifier: Programming Language :: Python :: 3
Classifier: Programming Language :: Python :: 3 :: Only
Classifier: Programming Language :: Python :: Implementation :: CPython
Classifier: Programming Language :: Python :: Implementation :: PyPy
Requires-Python: >=3.9
License-File: LICENSE
Requires-Dist: beautifulsoup4
Requires-Dist: PyMuPDF
Requires-Dist: sqlalchemy
Requires-Dist: psycopg2-binary
Requires-Dist: python-whois
Requires-Dist: polyfile
Requires-Dist: requests
Requires-Dist: pikepdf
Requires-Dist: python-dateutil
Requires-Dist: numpy
Requires-Dist: opencv-python
Requires-Dist: pyppeteer
Requires-Dist: tldextract
Requires-Dist: shodan
Requires-Dist: pillow
Requires-Dist: ImageHash
Requires-Dist: urllib3
Requires-Dist: termcolor
Requires-Dist: pytesseract
Requires-Dist: python-magic-bin==0.4.14
Requires-Dist: datefinder
Requires-Dist: qreader
Dynamic: license-file
